xml_models/__init__.py
xml_models/managers.py
xml_models/xml_models.py
xml_models/xpath_finder.py
xml_models/rest_client/__init__.py
xml_models/rest_client/rest_client.py
xml_models2-0.11.1.dist-info/DESCRIPTION.rst
xml_models2-0.11.1.dist-info/METADATA
xml_models2-0.11.1.dist-info/RECORD
xml_models2-0.11.1.dist-info/WHEEL
xml_models2-0.11.1.dist-info/metadata.json
xml_models2-0.11.1.dist-info/top_level.txt
