Metadata-Version: 2.0
Name: xml-models2
Version: 0.11.1
Summary: XML backed models queried from external REST apis
Home-page: http://github.com/alephnullplex/xml_models2
Author: Geoff Ford and Chris Tarttelin and Cam McHugh
Author-email: g_ford@hotmail.ccom
License: UNKNOWN
Platform: UNKNOWN
Requires-Dist: future
Requires-Dist: lxml
Requires-Dist: python-dateutil
Requires-Dist: pytz
Requires-Dist: requests
